Metadata-Version: 2.1
Name: AutoGUIX
Version: 0.0.4
Summary: AutoGUIX is the extended version of PyAutoGUI. Few features are added with the help of PyGetWindow and PyAutoGUI.
Home-page: https://github.com/4akhilkumar/autoguix
Author: Sai Akhil Kumar Reddy N
Author-email: 4akhilkumar@gmail.com
License: BSD
Keywords: gui automation test testing python commands keyboard press keystroke
Platform: UNKNOWN
Classifier: Development Status :: 4 - Beta
Classifier: Intended Audience :: Developers
Classifier: License :: OSI Approved :: BSD License
Classifier: Programming Language :: Python :: 3
Classifier: Programming Language :: Python :: 3.7
Classifier: Programming Language :: Python :: 3.8
Classifier: Programming Language :: Python :: 3.9
